scientific_spinbox/__init__.py
scientific_spinbox/defaults.py
scientific_spinbox/validators.py
scientific_spinbox/widget.py
scientific_spinbox/backend/__init__.py
scientific_spinbox/backend/interfaces.py
scientific_spinbox/backend/utils.py
scientific_spinbox/errors/__init__.py
scientific_spinbox/errors/backend.py
scientific_spinbox/errors/validators.py
scientific_spinbox/errors/widget.py
scientific_spinbox-1.0.1b1.dist-info/licenses/LICENSE.rst
test_gui/__init__.py
test_gui/dlg_shortexample_gui.py
test_gui/dlg_test_externals.py
test_gui/dlg_test_gui.py
test_gui/ui/__init__.py
test_gui/ui/dlg_testspinbox_externals.py
test_gui/ui/dlg_testspinbox_externals_ui.py
test_gui/ui/dlg_testspinbox_gui.py
test_gui/ui/dlg_testspinbox_shortexample_gui.py
tests/__init__.py
tests/conftest.py
tests/test_defaults.py
scientific_spinbox-1.0.1b1.dist-info/METADATA
scientific_spinbox-1.0.1b1.dist-info/WHEEL
scientific_spinbox-1.0.1b1.dist-info/top_level.txt
scientific_spinbox-1.0.1b1.dist-info/RECORD
