Metadata-Version: 2.4
Name: scientific-spinbox
Version: 1.0.1b1
Summary: ScientificSpinbox - A Qt widget to manipulate physical quantities
Author: ['Breno Pelegrin']
Author-email: brenohqsilva@gmail.com
Maintainer: ['Breno Pelegrin <brenohqsilva@gmail.com>', 'Daniel Cosmo Pizetta <daniel.pizetta@alumni.usp.br>']
Maintainer-email: ['brenohqsilva@gmail.com', 'daniel.pizetta@alumni.usp.br']
License: LGPLv3
Project-URL: Homepage, https://dpizetta.gitlab.io/pqwidget
Project-URL: Documentation, https://pqwidget.readthedocs.io/
Project-URL: Source, https://gitlab.com/dpizetta/pqwidget
Project-URL: Issues, https://gitlab.com/dpizetta/pqwidget/issues
Classifier: Development Status :: 4 - Beta
Classifier: Environment :: X11 Applications :: Qt
Classifier: Environment :: Plugins
Classifier: Intended Audience :: Science/Research
Classifier: Intended Audience :: End Users/Desktop
Classifier: Intended Audience :: Developers
Classifier: License :: OSI Approved :: GNU Lesser General Public License v3 (LGPLv3)
Classifier: Natural Language :: English
Classifier: Operating System :: MacOS
Classifier: Operating System :: Microsoft :: Windows
Classifier: Operating System :: POSIX :: Linux
Classifier: Programming Language :: Python :: 3
Classifier: Topic :: Scientific/Engineering
Classifier: Topic :: Software Development :: User Interfaces
Classifier: Topic :: Text Editors :: Text Processing
License-File: LICENSE.rst
Requires-Dist: pint
Requires-Dist: pyqt5
Requires-Dist: qtpy
Dynamic: author
Dynamic: author-email
Dynamic: classifier
Dynamic: description
Dynamic: description-content-type
Dynamic: license
Dynamic: license-file
Dynamic: maintainer
Dynamic: maintainer-email
Dynamic: project-url
Dynamic: requires-dist
Dynamic: summary
